<?xml version="1.0" encoding="UTF-8" standalone="no" ?>
<archive>

  <version>2.0.0</version>

  <catalog modify_description="0" modify_info="0" modify_name="0" modify_thumbnail="0" uuid="393dd3607e-3149-87b0-b262-f50bb2bb61">
    <type>material</type>
    <readonly>1</readonly>
    <share_edit_flag>0</share_edit_flag>
    <uploadable>0</uploadable>
    <tool company="celsys" name="paint" version="1.1.0"/>
    <name>握紧球棒</name>
    <groups>
      <group modify_description="0" modify_info="0" modify_name="0" modify_thumbnail="0" parentuuid="" uuid="e21b4b80f4-ff40-0b9a-0987-da27101c71">
        <tool company="celsys" name="paint" version="1.1.0"/>
        <type ver="1.0.0">material</type>
        <name></name>
        <required>0</required>
        <reserveId>0</reserveId>
        <reserveWait>0</reserveWait>
        <items>
          <item modify_description="0" modify_info="0" modify_name="0" modify_thumbnail="0" parentuuid="" uuid="403dc4f242-bf48-2183-73d4-9875414edb">
            <tool company="celsys" name="paint" version="1.1.0"/>
            <type ver="1.0.0">pose</type>
            <name>握紧球棒</name>
            <required>0</required>
            <reserveId>0</reserveId>
            <reserveWait>0</reserveWait>
            <thumbnail>
              <fileref idref="cc6adc9a1d-6b4c-d3bc-7952-76560ac72a"/>
            </thumbnail>
            <data>
              <fileref idref="f69bd6062e-8345-cda7-ff1f-bc85e5e264"/>
            </data>
            <icedata>
              <fileref idref="68b090707c-e14e-7b98-0d77-00a25c1543"/>
            </icedata>
          </item>
        </items>
      </group>
    </groups>
    <region/>
  </catalog>

  <files>
    <file document="false" encrypt="false" id="68b090707c-e14e-7b98-0d77-00a25c1543" mime="text/xml">
      <path>icedata/layerData.xml</path>
    </file>
    <file document="false" encrypt="false" id="cc6adc9a1d-6b4c-d3bc-7952-76560ac72a" mime="image/png">
      <path>thumbnail/thumbnail.png</path>
    </file>
    <file document="false" encrypt="true" id="f69bd6062e-8345-cda7-ff1f-bc85e5e264" mime="application/octet-stream">
      <path>data/material.pose</path>
    </file>
  </files>

</archive>
