<?xml version="1.0" encoding="UTF-8" standalone="no" ?>
<archive>

  <version>2.0.0</version>

  <catalog modify_description="0" modify_info="0" modify_name="0" modify_thumbnail="0" uuid="e7056f8093-2242-c0b1-2912-23d2cd24e6">
    <type>material</type>
    <readonly>1</readonly>
    <share_edit_flag>0</share_edit_flag>
    <uploadable>0</uploadable>
    <tool company="celsys" name="paint" version="1.1.1"/>
    <name>50% 圆 S</name>
    <groups>
      <group modify_description="0" modify_info="0" modify_name="0" modify_thumbnail="0" parentuuid="" uuid="546530b947-9b44-488a-5197-e0715177d9">
        <tool company="celsys" name="paint" version="1.1.1"/>
        <type ver="1.0.0">material</type>
        <name></name>
        <required>0</required>
        <reserveId>0</reserveId>
        <reserveWait>0</reserveWait>
        <items>
          <item modify_description="0" modify_info="0" modify_name="0" modify_thumbnail="0" parentuuid="" uuid="9944fd5f09-e140-9da6-c908-8ecbb91a33">
            <tool company="celsys" name="paint" version="1.1.1"/>
            <type ver="1.0.0">image</type>
            <name>50% 圆 S</name>
            <required>0</required>
            <reserveId>0</reserveId>
            <reserveWait>0</reserveWait>
            <thumbnail>
              <fileref idref="ad17ec63db-3749-d0a9-a7f5-e9a00781c1"/>
            </thumbnail>
            <data>
              <fileref idref="c087b29ce1-f847-e6a6-2ac3-267d90b526"/>
            </data>
            <icedata>
              <fileref idref="eaa4ae2511-fb4c-04b3-7d99-52ce6ddc7a"/>
            </icedata>
          </item>
        </items>
      </group>
    </groups>
    <region/>
  </catalog>

  <files>
    <file document="false" encrypt="false" id="ad17ec63db-3749-d0a9-a7f5-e9a00781c1" mime="image/png">
      <path>thumbnail/thumbnail.png</path>
    </file>
    <file document="false" encrypt="true" id="c087b29ce1-f847-e6a6-2ac3-267d90b526" mime="application/octet-stream">
      <path>data/material.layer</path>
    </file>
    <file document="false" encrypt="false" id="eaa4ae2511-fb4c-04b3-7d99-52ce6ddc7a" mime="text/xml">
      <path>icedata/layerData.xml</path>
    </file>
  </files>

</archive>
