<?xml version="1.0" encoding="UTF-8" standalone="no" ?>
<archive>

  <version>2.0.0</version>

  <catalog modify_description="0" modify_info="0" modify_name="0" modify_thumbnail="0" uuid="147304e413-0f4e-9686-766d-e4d2701879">
    <type>material</type>
    <readonly>1</readonly>
    <share_edit_flag>0</share_edit_flag>
    <uploadable>0</uploadable>
    <tool company="celsys" name="paint" version="1.1.0"/>
    <name>警戒线</name>
    <groups>
      <group modify_description="0" modify_info="0" modify_name="0" modify_thumbnail="0" parentuuid="" uuid="ffc2d957c3-4540-1796-9474-bb4f871948">
        <tool company="celsys" name="paint" version="1.1.0"/>
        <type ver="1.0.0">material</type>
        <name></name>
        <required>0</required>
        <reserveId>0</reserveId>
        <reserveWait>0</reserveWait>
        <items>
          <item modify_description="0" modify_info="0" modify_name="0" modify_thumbnail="0" parentuuid="" uuid="112fb7216b-b14a-c3bf-311a-784c84a751">
            <tool company="celsys" name="paint" version="1.1.0"/>
            <type ver="1.0.0">image</type>
            <name>警戒线</name>
            <required>0</required>
            <reserveId>0</reserveId>
            <reserveWait>0</reserveWait>
            <thumbnail>
              <fileref idref="aa667855ec-d747-bd87-3659-dce153ddf8"/>
            </thumbnail>
            <data>
              <fileref idref="cbce29cb33-304c-fca3-8f88-0fbfe34bd8"/>
            </data>
            <icedata>
              <fileref idref="457636c27b-fb42-95be-b266-6aed7463c9"/>
            </icedata>
          </item>
        </items>
      </group>
    </groups>
    <region/>
  </catalog>

  <files>
    <file document="false" encrypt="false" id="457636c27b-fb42-95be-b266-6aed7463c9" mime="text/xml">
      <path>icedata/layerData.xml</path>
    </file>
    <file document="false" encrypt="false" id="aa667855ec-d747-bd87-3659-dce153ddf8" mime="image/png">
      <path>thumbnail/thumbnail.png</path>
    </file>
    <file document="false" encrypt="true" id="cbce29cb33-304c-fca3-8f88-0fbfe34bd8" mime="application/octet-stream">
      <path>data/material.layer</path>
    </file>
  </files>

</archive>
