<?xml version="1.0" encoding="UTF-8" standalone="no" ?>
<archive>

  <version>2.0.0</version>

  <catalog modify_description="0" modify_info="0" modify_name="0" modify_thumbnail="0" uuid="c4c81580e8-2d43-6fa2-4877-2f2dd3ac63">
    <type>material</type>
    <readonly>1</readonly>
    <share_edit_flag>0</share_edit_flag>
    <uploadable>0</uploadable>
    <tool company="celsys" name="paint" version="1.1.0"/>
    <name>单色</name>
    <groups>
      <group modify_description="0" modify_info="0" modify_name="0" modify_thumbnail="0" parentuuid="" uuid="e2c2814cd1-f944-8a92-ce0b-4d8e07c2ec">
        <tool company="celsys" name="paint" version="1.1.0"/>
        <type ver="1.0.0">material</type>
        <name></name>
        <required>0</required>
        <reserveId>0</reserveId>
        <reserveWait>0</reserveWait>
        <items>
          <item modify_description="0" modify_info="0" modify_name="0" modify_thumbnail="0" parentuuid="" uuid="421b686bc6-db42-8c9f-cbee-de9662627b">
            <tool company="celsys" name="paint" version="1.1.0"/>
            <type ver="1.0.0">image</type>
            <name>单色</name>
            <required>0</required>
            <reserveId>0</reserveId>
            <reserveWait>0</reserveWait>
            <thumbnail>
              <fileref idref="72f52dac31-f842-36b6-f882-1a751db27e"/>
            </thumbnail>
            <data>
              <fileref idref="5d80ad49ce-a64d-8d89-5f76-184d9d4550"/>
            </data>
            <icedata>
              <fileref idref="017058bb12-4245-91a1-8b9b-1d6b0e5384"/>
            </icedata>
          </item>
        </items>
      </group>
    </groups>
    <region/>
  </catalog>

  <files>
    <file document="false" encrypt="false" id="017058bb12-4245-91a1-8b9b-1d6b0e5384" mime="text/xml">
      <path>icedata/layerData.xml</path>
    </file>
    <file document="false" encrypt="true" id="5d80ad49ce-a64d-8d89-5f76-184d9d4550" mime="application/octet-stream">
      <path>data/material.layer</path>
    </file>
    <file document="false" encrypt="false" id="72f52dac31-f842-36b6-f882-1a751db27e" mime="image/png">
      <path>thumbnail/thumbnail.png</path>
    </file>
  </files>

</archive>
