<?xml version="1.0" encoding="UTF-8" standalone="no" ?>
<archive>

  <version>2.0.0</version>

  <catalog modify_description="0" modify_info="0" modify_name="0" modify_thumbnail="0" uuid="1dd8d10215-034a-2a9a-2546-c67fd19880">
    <type>material</type>
    <readonly>1</readonly>
    <share_edit_flag>0</share_edit_flag>
    <uploadable>0</uploadable>
    <tool company="celsys" name="paint" version="1.2.1"/>
    <name>消石灰</name>
    <groups>
      <group modify_description="0" modify_info="0" modify_name="0" modify_thumbnail="0" parentuuid="" uuid="33ff0a95a3-cb4a-06ac-44e1-14596251ec">
        <tool company="celsys" name="paint" version="1.2.1"/>
        <type ver="1.0.0">material</type>
        <name></name>
        <required>0</required>
        <reserveId>0</reserveId>
        <reserveWait>0</reserveWait>
        <items>
          <item modify_description="0" modify_info="0" modify_name="0" modify_thumbnail="0" parentuuid="" uuid="a759eac176-944a-45aa-77d6-a76bb2c8a8">
            <tool company="celsys" name="paint" version="1.2.1"/>
            <type ver="1.0.0">image</type>
            <name>消石灰</name>
            <required>0</required>
            <reserveId>0</reserveId>
            <reserveWait>0</reserveWait>
            <thumbnail>
              <fileref idref="f574066c76-fd49-1986-9f54-34ea6f07d9"/>
            </thumbnail>
            <data>
              <fileref idref="df17e8def3-7d40-24ac-5203-132e022672"/>
            </data>
            <icedata>
              <fileref idref="fb021eb2cd-3c43-8487-e2d7-13c6bf2aea"/>
            </icedata>
          </item>
        </items>
      </group>
    </groups>
    <region/>
  </catalog>

  <files>
    <file document="false" encrypt="true" id="df17e8def3-7d40-24ac-5203-132e022672" mime="application/octet-stream">
      <path>data/material_0.layer</path>
    </file>
    <file document="false" encrypt="false" id="f574066c76-fd49-1986-9f54-34ea6f07d9" mime="image/png">
      <path>thumbnail/thumbnail.png</path>
    </file>
    <file document="false" encrypt="false" id="fb021eb2cd-3c43-8487-e2d7-13c6bf2aea" mime="text/xml">
      <path>icedata/layerData.xml</path>
    </file>
  </files>

</archive>
